[
    {
        "Name": "Microsoft",
        "City": "Tokyo",
        "Zone": "North",
        "LinkedIn Followers": 3421,
        "Industry": "IT Services",
        "Company Size": "100-500 employees",
        "Headquarters": "New York, USA",
        "Company Type": "Private",
        "Segment Tags": "Quantum Computing",
        "People Associated": "Emily Johnson - Chief Executive Officer (CEO)"
    },
    {
        "Name": "Adobe",
        "City": "New York City",
        "Zone": "East",
        "LinkedIn Followers": 8978,
        "Industry": "HR",
        "Company Size": "500-1,000 employees",
        "Headquarters": "Tokyo, Japan",
        "Company Type": "Public",
        "Segment Tags": "Blockchain Development",
        "People Associated": "Daniel Rodriguez - Senior Software Engineer"
    },
    {
        "Name": "Twilio",
        "City": "London",
        "Zone": "West",
        "LinkedIn Followers": 23567,
        "Industry": "Manufacturing",
        "Company Size": "50-100 employees",
        "Headquarters": "London, UK",
        "Company Type": "Private",
        "Segment Tags": "Augmented Reality",
        "People Associated": "Jessica Thompson - Marketing Manager"
    },
    {
        "Name": "Genesys",
        "City": "Paris",
        "Zone": "South",
        "LinkedIn Followers": 12045,
        "Industry": "Healthcare",
        "Company Size": "1,000-5,000 employees",
        "Headquarters": "Mumbai, India",
        "Company Type": "Public",
        "Segment Tags": "Cybersecurity Solutions",
        "People Associated": "Michael Lee - Chief Financial Officer (CFO)"
    },
    {
        "Name": "Nutanix",
        "City": "Beijing",
        "Zone": "North-East",
        "LinkedIn Followers": 2,
        "Industry": "Financial Services",
        "Company Size": "10,000+ employees",
        "Headquarters": "Sydney, Australia",
        "Company Type": "Private",
        "Segment Tags": "Robotic Process Automation",
        "People Associated": "Ashley Miller - Human Resources Specialist"
    },
    {
        "Name": "MathWorks",
        "City": "Sydney",
        "Zone": "South-West",
        "LinkedIn Followers": 123,
        "Industry": "Retail",
        "Company Size": "5,000-10,000 employees",
        "Headquarters": "Berlin, Germany",
        "Company Type": "Public",
        "Segment Tags": "3D Printing Technology",
        "People Associated": "Brian Turner - Data Analyst"
    },
    {
        "Name": "Qualtrics",
        "City": "Rio de Janeiro",
        "Zone": "North-West",
        "LinkedIn Followers": 1234242,
        "Industry": "Hospitality",
        "Company Size": "100-500 employees",
        "Headquarters": "Sao Paulo, Brazil",
        "Company Type": "Private",
        "Segment Tags": "Cloud Computing",
        "People Associated": "Megan Carter - Chief Operating Officer (COO)"
    },
    {
        "Name": "Cvent",
        "City": "Cairo",
        "Zone": "South-East",
        "LinkedIn Followers": 7890,
        "Industry": "Agriculture",
        "Company Size": "10,000+ employees",
        "Headquarters": "Beijing, China",
        "Company Type": "Public",
        "Segment Tags": "Internet of Things (IoT)",
        "People Associated": "Ryan Baker - UX/UI Designer"
    },
    {
        "Name": "Snowflake",
        "City": "Mumbai",
        "Zone": "West-Northwest",
        "LinkedIn Followers": 15000,
        "Industry": "Education",
        "Company Size": "1,000-5,000 employees",
        "Headquarters": "Paris, France",
        "Company Type": "Private",
        "Segment Tags": "Biometric Authentication",
        "People Associated": "Sarah Lewis - Project Manager"
    },
    {
        "Name": "Zscaler",
        "City": "Moscow",
        "Zone": "East-Southeast",
        "LinkedIn Followers": 4567,
        "Industry": "IT Services",
        "Company Size": "500-1,000 employees",
        "Headquarters": "Toronto, Canada",
        "Company Type": "Public",
        "Segment Tags": "Natural Language Processing",
        "People Associated": "Christopher Taylor - Research Scientist"
    },
    {
        "Name": "Pure Storage",
        "City": "Toronto",
        "Zone": "South-Southwest",
        "LinkedIn Followers": 23098,
        "Industry": "Real Estate",
        "Company Size": "50-100 employees",
        "Headquarters": "Moscow, Russia",
        "Company Type": "Private",
        "Segment Tags": "Virtual Reality Systems",
        "People Associated": "Olivia Martinez - Customer Support Specialist"
    },
    {
        "Name": "UiPath",
        "City": "Istanbul",
        "Zone": "North-Northeast",
        "LinkedIn Followers": 8765,
        "Industry": "Manufacturing",
        "Company Size": "5,000-10,000 employees",
        "Headquarters": "Johannesburg, South Africa",
        "Company Type": "Public",
        "Segment Tags": "Edge Computing",
        "People Associated": "Justin Wright - Sales Representative"
    },
    {
        "Name": "GitHub",
        "City": "Buenos Aires",
        "Zone": "East-Northeast",
        "LinkedIn Followers": 9876,
        "Industry": "Energy",
        "Company Size": "100-500 employees",
        "Headquarters": "Seoul, South Korea",
        "Company Type": "Private",
        "Segment Tags": "DevOps Automation",
        "People Associated": "Hannah Brown - Product Manager"
    },
    {
        "Name": "mongoDB",
        "City": "Seoul",
        "Zone": "West-Southwest",
        "LinkedIn Followers": 34567,
        "Industry": "Automotive",
        "Company Size": "50-100 employees",
        "Headquarters": "Istanbul, Turkey",
        "Company Type": "Public",
        "Segment Tags": "Chatbot Development",
        "People Associated": "Ethan Davis - IT Administrator"
    },
    {
        "Name": "Dropbox",
        "City": "Berlin",
        "Zone": "South-Southeast",
        "LinkedIn Followers": 56000,
        "Industry": "IT Services",
        "Company Size": "1,000-5,000 employees",
        "Headquarters": "Mexico City, Mexico",
        "Company Type": "Private",
        "Segment Tags": "Machine Learning Frameworks",
        "People Associated": "Lauren Hall - Chief Marketing Officer (CMO)"
    },
    {
        "Name": "Databricks",
        "City": "Bangkok",
        "Zone": "North-Northwest",
        "LinkedIn Followers": 2300,
        "Industry": "HR",
        "Company Size": "10,000+ employees",
        "Headquarters": "Cairo, Egypt",
        "Company Type": "Public",
        "Segment Tags": "Edge AI",
        "People Associated": "Joshua Clark - Network Engineer"
    },
    {
        "Name": "Altimetrik",
        "City": "Los Angeles",
        "Zone": "West-Northeast",
        "LinkedIn Followers": 987,
        "Industry": "Aerospace",
        "Company Size": "500-1,000 employees",
        "Headquarters": "Buenos Aires, Argentina",
        "Company Type": "Private",
        "Segment Tags": "Big Data Analytics",
        "People Associated": "Natalie White - Operations Manager"
    },
    {
        "Name": "Datadog",
        "City": "Mexico City",
        "Zone": "South-Northeast",
        "LinkedIn Followers": 78000,
        "Industry": "Entertainment",
        "Company Size": "10,000+ employees",
        "Headquarters": "Jakarta, Indonesia",
        "Company Type": "Public",
        "Segment Tags": "Neural Networks",
        "People Associated": "Brandon Murphy - Graphic Designer"
    },
    {
        "Name": "Slack",
        "City": "Dubai",
        "Zone": "East-Southwest",
        "LinkedIn Followers": 1234,
        "Industry": "Telecom",
        "Company Size": "1,000-5,000 employees",
        "Headquarters": "Riyadh, Saudi Arabia",
        "Company Type": "Private",
        "Segment Tags": "Drone Technology",
        "People Associated": "Samantha Adams - Software Developer"
    },
    {
        "Name": "Dynatrace",
        "City": "Rome",
        "Zone": "North-Southeast",
        "LinkedIn Followers": 56789,
        "Industry": "Manufacturing",
        "Company Size": "5,000-10,000 employees",
        "Headquarters": "Bangkok, Thailand",
        "Company Type": "Public",
        "Segment Tags": "Sensor Fusion",
        "People Associated": "Kevin Hill - Chief Technology Officer (CTO)"
    },
    {
        "Name": "Toast",
        "City": "Amsterdam",
        "Zone": "East-Northwest",
        "LinkedIn Followers": 30000,
        "Industry": "IT Services",
        "Company Size": "50-100 employees",
        "Headquarters": "Amsterdam, Netherlands",
        "Company Type": "Private",
        "Segment Tags": "Wearable Technology",
        "People Associated": "Emma Green - Content Writer"
    },
    {
        "Name": "Box ",
        "City": "Cape Town",
        "Zone": "South-Northwest",
        "LinkedIn Followers": 876,
        "Industry": "Retail",
        "Company Size": "10,000+ employees",
        "Headquarters": "Dublin, Ireland",
        "Company Type": "Public",
        "Segment Tags": "Edge Analytics",
        "People Associated": "Jason Allen - Business Analyst"
    },
    {
        "Name": "Procore",
        "City": "Barcelona",
        "Zone": "West-Southeast",
        "LinkedIn Followers": 45000,
        "Industry": "Agriculture",
        "Company Size": "100-500 employees",
        "Headquarters": "Singapore City, Singapore",
        "Company Type": "Private",
        "Segment Tags": "Geospatial Technology",
        "People Associated": "Victoria Scott - Quality Assurance Engineer"
    },
    {
        "Name": "Smartsheet ",
        "City": "Jakarta",
        "Zone": "Southeast",
        "LinkedIn Followers": 789,
        "Industry": "Healthcare",
        "Company Size": "500-1,000 employees",
        "Headquarters": "Helsinki, Finland",
        "Company Type": "Public",
        "Segment Tags": "Fintech Solutions",
        "People Associated": "Nicholas Garcia - Data Scientist"
    },
    {
        "Name": "Coupa Software ",
        "City": "Vancouver",
        "Zone": "Northwest",
        "LinkedIn Followers": 89000,
        "Industry": "IT Services",
        "Company Size": "5,000-10,000 employees",
        "Headquarters": "Copenhagen, Denmark",
        "Company Type": "Private",
        "Segment Tags": "Voice Recognition Systems",
        "People Associated": "Kayla Roberts - Public Relations Coordinator"
    },
    {
        "Name": "Progress",
        "City": "Singapore",
        "Zone": "Northeast",
        "LinkedIn Followers": 23456,
        "Industry": "Education",
        "Company Size": "1,000-5,000 employees",
        "Headquarters": "Oslo, Norway",
        "Company Type": "Public",
        "Segment Tags": "Quantum Cryptography",
        "People Associated": "Eric Turner - Systems Administrator"
    },
    {
        "Name": "Zoho",
        "City": "Prague",
        "Zone": "Southwest",
        "LinkedIn Followers": 10000,
        "Industry": "Financial Services",
        "Company Size": "50-100 employees",
        "Headquarters": "Stockholm, Sweden",
        "Company Type": "Private",
        "Segment Tags": "Autonomous Vehicles",
        "People Associated": "Allison Carter - Chief Creative Officer (CCO)"
    },
    {
        "Name": "Infobip",
        "City": "Helsinki",
        "Zone": "West-North",
        "LinkedIn Followers": 67890,
        "Industry": "Hospitality",
        "Company Size": "1,000-5,000 employees",
        "Headquarters": "Warsaw, Poland",
        "Company Type": "Public",
        "Segment Tags": "Genetic Engineering",
        "People Associated": "Derek Foster - Financial Analyst"
    },
    {
        "Name": "Mulesoft",
        "City": "Nairobi",
        "Zone": "East-South",
        "LinkedIn Followers": 12345,
        "Industry": "Manufacturing",
        "Company Size": "500-1,000 employees",
        "Headquarters": "Rome, Italy",
        "Company Type": "Private",
        "Segment Tags": "Smart Grid Technology",
        "People Associated": "Rachel Turner - User Experience Researcher"
    },
    {
        "Name": "Rapid7",
        "City": "San Francisco",
        "Zone": "South-West",
        "LinkedIn Followers": 32000,
        "Industry": "HR",
        "Company Size": "50-100 employees",
        "Headquarters": "Vienna, Austria",
        "Company Type": "Public",
        "Segment Tags": "Gesture Control Interfaces",
        "People Associated": "Kyle Johnson - Customer Success Manager"
    },
    {
        "Name": "Asana",
        "City": "Cairo",
        "Zone": "North-East",
        "LinkedIn Followers": 78900,
        "Industry": "Real Estate",
        "Company Size": "5,000-10,000 employees",
        "Headquarters": "Prague, Czech Republic",
        "Company Type": "Private",
        "Segment Tags": "Quantum Machine Learning",
        "People Associated": "Lauren Hall - Chief Marketing Officer (CMO)"
    },
    {
        "Name": "Anaplan",
        "City": "Riyadh",
        "Zone": "West-South",
        "LinkedIn Followers": 2345,
        "Industry": "Energy",
        "Company Size": "1,000-5,000 employees",
        "Headquarters": "Budapest, Hungary",
        "Company Type": "Public",
        "Segment Tags": "Biomedical Imaging",
        "People Associated": "Tyler Brown - Technical Support Specialist"
    },
    {
        "Name": "New Relic",
        "City": "Athens",
        "Zone": "Southeast-East",
        "LinkedIn Followers": 60000,
        "Industry": "IT Services",
        "Company Size": "100-500 employees",
        "Headquarters": "Athens, Greece",
        "Company Type": "Private",
        "Segment Tags": "Swarm Robotics",
        "People Associated": "Megan Rodriguez - Social Media Manager"
    },
    {
        "Name": "Jamf",
        "City": "Warsaw",
        "Zone": "Northwest-West",
        "LinkedIn Followers": 87654,
        "Industry": "Automotive",
        "Company Size": "10,000+ employees",
        "Headquarters": "Lisbon, Portugal",
        "Company Type": "Public",
        "Segment Tags": "Predictive Analytics",
        "People Associated": "Jordan Smith - Sales Manager"
    },
    {
        "Name": "SPS Commerce ",
        "City": "Auckland",
        "Zone": "Northeast-North",
        "LinkedIn Followers": 5432,
        "Industry": "Telecom",
        "Company Size": "50-100 employees",
        "Headquarters": "Madrid, Spain",
        "Company Type": "Private",
        "Segment Tags": "Smart Home Automation",
        "People Associated": "Emily Wright - Chief Information Officer (CIO)"
    },
    {
        "Name": "Samsara",
        "City": "Budapest",
        "Zone": "Southwest-South",
        "LinkedIn Followers": 25000,
        "Industry": "IT Services",
        "Company Size": "5,000-10,000 employees",
        "Headquarters": "Brussels, Belgium",
        "Company Type": "Public",
        "Segment Tags": "Bioinformatics",
        "People Associated": "Mason Robinson - Content Marketing Specialist"
    },
    {
        "Name": "Appian",
        "City": "Kuala Lumpur",
        "Zone": "South-Southeast",
        "LinkedIn Followers": 98765,
        "Industry": "Entertainment",
        "Company Size": "500-1,000 employees",
        "Headquarters": "Zurich, Switzerland",
        "Company Type": "Private",
        "Segment Tags": "Cloud-Native Applications",
        "People Associated": "Jennifer Morris - Senior Project Manager"
    },
    {
        "Name": "Diligent",
        "City": "Stockholm",
        "Zone": "North-Northeast",
        "LinkedIn Followers": 21000,
        "Industry": "Agriculture",
        "Company Size": "10,000+ employees",
        "Headquarters": "Vienna, Austria",
        "Company Type": "Public",
        "Segment Tags": "Swarm Intelligence",
        "People Associated": "Logan Thomas - Cybersecurity Analyst"
    },
    {
        "Name": "SailPoint",
        "City": "Lima",
        "Zone": "East-Northeast",
        "LinkedIn Followers": 78901,
        "Industry": "HR",
        "Company Size": "1,000-5,000 employees",
        "Headquarters": "Helsinki, Finland",
        "Company Type": "Private",
        "Segment Tags": "Explainable AI",
        "People Associated": "Emily Martinez - Chief People Officer (CPO)"
    },
    {
        "Name": "Miro",
        "City": "Copenhagen",
        "Zone": "West-Southwest",
        "LinkedIn Followers": 123,
        "Industry": "Retail",
        "Company Size": "50-100 employees",
        "Headquarters": "Copenhagen, Denmark",
        "Company Type": "Public",
        "Segment Tags": "Renewable Energy Technology",
        "People Associated": "Nathan Turner - Front-end Developer"
    },
    {
        "Name": "SonicWall",
        "City": "Dublin",
        "Zone": "South-Northeast",
        "LinkedIn Followers": 43000,
        "Industry": "Manufacturing",
        "Company Size": "5,000-10,000 employees",
        "Headquarters": "Oslo, Norway",
        "Company Type": "Private",
        "Segment Tags": "Quantum Sensors",
        "People Associated": "Abigail King - Event Coordinator"
    },
    {
        "Name": "BlackLine",
        "City": "Manila",
        "Zone": "North-Northwest",
        "LinkedIn Followers": 678,
        "Industry": "Education",
        "Company Size": "500-1,000 employees",
        "Headquarters": "Stockholm, Sweden",
        "Company Type": "Public",
        "Segment Tags": "Gesture Recognition Technology",
        "People Associated": "Carter Brooks - Database Administrator"
    },
    {
        "Name": "DataRobot",
        "City": "Warsaw",
        "Zone": "West-Northeast",
        "LinkedIn Followers": 5600,
        "Industry": "Healthcare",
        "Company Size": "100-500 employees",
        "Headquarters": "Warsaw, Poland",
        "Company Type": "Private",
        "Segment Tags": "Intelligent Automation",
        "People Associated": "Ashley Campbell - Business Development Manager"
    },
    {
        "Name": "Relativity",
        "City": "Vienna",
        "Zone": "East-Southwest",
        "LinkedIn Followers": 780,
        "Industry": "Financial Services",
        "Company Size": "10,000+ employees",
        "Headquarters": "Rome, Italy",
        "Company Type": "Public",
        "Segment Tags": "Edge Security",
        "People Associated": "Evan Powell - Machine Learning Engineer"
    },
    {
        "Name": "Phreesia",
        "City": "Zurich",
        "Zone": "South-Southeast",
        "LinkedIn Followers": 1500,
        "Industry": "Aerospace",
        "Company Size": "1,000-5,000 employees",
        "Headquarters": "Vienna, Austria",
        "Company Type": "Private",
        "Segment Tags": "Quantum Networking",
        "People Associated": "Sydney Foster - Chief Legal Officer (CLO)"
    },
    {
        "Name": "Klaviyo",
        "City": "Bras\u00c3\u00adlia",
        "Zone": "North-Southwest",
        "LinkedIn Followers": 9870,
        "Industry": "IT Services",
        "Company Size": "10,000+ employees",
        "Headquarters": "Prague, Czech Republic",
        "Company Type": "Public",
        "Segment Tags": "Autonomous Drones",
        "People Associated": "Gavin Turner - Cloud Solutions Architect"
    },
    {
        "Name": "Seismic",
        "City": "Oslo",
        "Zone": "South-Northwest",
        "LinkedIn Followers": 34000,
        "Industry": "Real Estate",
        "Company Size": "50-100 employees",
        "Headquarters": "Budapest, Hungary",
        "Company Type": "Private",
        "Segment Tags": "Dark Web Analysis",
        "People Associated": "Chloe White - UX/UI Researcher"
    },
    {
        "Name": "Kinaxis",
        "City": "Warsaw",
        "Zone": "Northwest-South",
        "LinkedIn Followers": 567,
        "Industry": "Energy",
        "Company Size": "5,000-10,000 employees",
        "Headquarters": "Athens, Greece",
        "Company Type": "Public",
        "Segment Tags": "Biohacking",
        "People Associated": "Owen Mitchell - Procurement Specialist"
    },
    {
        "Name": "Snyk",
        "City": "Munich",
        "Zone": "Northeast-North",
        "LinkedIn Followers": 890,
        "Industry": "Automotive",
        "Company Size": "100-500 employees",
        "Headquarters": "Lisbon, Portugal",
        "Company Type": "Private",
        "Segment Tags": "Quantum Information Science",
        "People Associated": "Lily Parker - Chief Diversity and Inclusion Officer (CDIO)"
    },
    {
        "Name": "Intercom ",
        "City": "Brussels",
        "Zone": "Southeast-West",
        "LinkedIn Followers": 69000,
        "Industry": "Telecom",
        "Company Size": "1,000-5,000 employees",
        "Headquarters": "Madrid, Spain",
        "Company Type": "Public",
        "Segment Tags": "Edge Storage Solutions",
        "People Associated": "Isaac Foster - Mobile App Developer"
    },
    {
        "Name": "Ping Identity",
        "City": "Helsinki",
        "Zone": "South-Southwest",
        "LinkedIn Followers": 45600,
        "Industry": "IT Services",
        "Company Size": "500-1,000 employees",
        "Headquarters": "Brussels, Belgium",
        "Company Type": "Private",
        "Segment Tags": "Space Technology",
        "People Associated": "Zoey Anderson - Chief Strategy Officer (CSO)"
    },
    {
        "Name": "Podium",
        "City": "Zurich",
        "Zone": "North-Northeast",
        "LinkedIn Followers": 8760,
        "Industry": "Manufacturing",
        "Company Size": "10,000+ employees",
        "Headquarters": "Zurich, Switzerland",
        "Company Type": "Public",
        "Segment Tags": "Nanotechnology",
        "People Associated": "Caleb Ross - Systems Analyst"
    },
    {
        "Name": "Tricentis",
        "City": "Riyadh",
        "Zone": "East-Northeast",
        "LinkedIn Followers": 98700,
        "Industry": "Hospitality",
        "Company Size": "100-500 employees",
        "Headquarters": "Vienna, Austria",
        "Company Type": "Private",
        "Segment Tags": "Quantum Algorithms",
        "People Associated": "Alexis Taylor - Customer Experience Specialist"
    },
    {
        "Name": "Mediaocean",
        "City": "Copenhagen",
        "Zone": "West-Southwest",
        "LinkedIn Followers": 2340,
        "Industry": "HR",
        "Company Size": "50-100 employees",
        "Headquarters": "Helsinki, Finland",
        "Company Type": "Public",
        "Segment Tags": "Energy Harvesting",
        "People Associated": "Dylan Baker - DevOps Engineer"
    },
    {
        "Name": "Planview",
        "City": "Bogot\u00c3\u00a1",
        "Zone": "Northeast-East",
        "LinkedIn Followers": 789000,
        "Industry": "Retail",
        "Company Size": "5,000-10,000 employees",
        "Headquarters": "Copenhagen, Denmark",
        "Company Type": "Private",
        "Segment Tags": "Brain-Computer Interface",
        "People Associated": "Maya Turner - Brand Manager"
    },
    {
        "Name": "WalkMe",
        "City": "Lisbon",
        "Zone": "Southwest-North",
        "LinkedIn Followers": 12340,
        "Industry": "IT Services",
        "Company Size": "1,000-5,000 employees",
        "Headquarters": "Oslo, Norway",
        "Company Type": "Public",
        "Segment Tags": "Quantum Key Distribution",
        "People Associated": "Aiden Wright - Chief Growth Officer (CGO)"
    },
    {
        "Name": "Lucid",
        "City": "Berlin",
        "Zone": "Southeast-Northwest",
        "LinkedIn Followers": 5670,
        "Industry": "Education",
        "Company Size": "10,000+ employees",
        "Headquarters": "Stockholm, Sweden",
        "Company Type": "Private",
        "Segment Tags": "Edge Database Management",
        "People Associated": "Jordan Reed - Full-stack Developer"
    },
    {
        "Name": "Gainsight",
        "City": "Madrid",
        "Zone": "Northwest-Southeast",
        "LinkedIn Followers": 89000,
        "Industry": "Agriculture",
        "Company Size": "500-1,000 employees",
        "Headquarters": "Warsaw, Poland",
        "Company Type": "Public",
        "Segment Tags": "Smart Agriculture Technology",
        "People Associated": "Addison Wilson - Talent Acquisition Specialist"
    },
    {
        "Name": "Domo",
        "City": "Amsterdam",
        "Zone": "South-North",
        "LinkedIn Followers": 67800,
        "Industry": "Entertainment",
        "Company Size": "50-100 employees",
        "Headquarters": "Rome, Italy",
        "Company Type": "Private",
        "Segment Tags": "Swarm Computing",
        "People Associated": "Mason Butler - Technical Writer"
    },
    {
        "Name": "Corel",
        "City": "Reykjavik",
        "Zone": "North-South",
        "LinkedIn Followers": 23000,
        "Industry": "IT Services",
        "Company Size": "1,000-5,000 employees",
        "Headquarters": "Vienna, Austria",
        "Company Type": "Public",
        "Segment Tags": "Autonomous Navigation",
        "People Associated": "Brooke Evans - Chief Sustainability Officer (CSO)"
    },
    {
        "Name": "Dataiku",
        "City": "Sydney",
        "Zone": "East-West",
        "LinkedIn Followers": 3450,
        "Industry": "Financial Services",
        "Company Size": "5,000-10,000 employees",
        "Headquarters": "Prague, Czech Republic",
        "Company Type": "Private",
        "Segment Tags": "Blockchain for Supply Chain",
        "People Associated": "Owen Bennett - UX/UI Designer"
    },
    {
        "Name": "Acquia",
        "City": "Ho Chi Minh City",
        "Zone": "West-East",
        "LinkedIn Followers": 560,
        "Industry": "Healthcare",
        "Company Size": "10,000+ employees",
        "Headquarters": "Budapest, Hungary",
        "Company Type": "Public",
        "Segment Tags": "Quantum Teleportation",
        "People Associated": "Paige Foster - Chief Customer Officer (CCO)"
    },
    {
        "Name": "Sprout Social",
        "City": "Casablanca",
        "Zone": "Southeast-Southwest",
        "LinkedIn Followers": 123000,
        "Industry": "Real Estate",
        "Company Size": "50-100 employees",
        "Headquarters": "Athens, Greece",
        "Company Type": "Private",
        "Segment Tags": "Edge Computing Security",
        "People Associated": "Leo Turner - IT Support Technician"
    },
    {
        "Name": "Intermedia",
        "City": "Buenos Aires",
        "Zone": "Southwest-Southeast",
        "LinkedIn Followers": 987000,
        "Industry": "Energy",
        "Company Size": "1,000-5,000 employees",
        "Headquarters": "Lisbon, Portugal",
        "Company Type": "Public",
        "Segment Tags": "Self-Healing Systems",
        "People Associated": "Stella Morris - Chief Revenue Officer (CRO)"
    },
    {
        "Name": "Druva",
        "City": "Warsaw",
        "Zone": "Northeast-Northwest",
        "LinkedIn Followers": 7890000,
        "Industry": "HR",
        "Company Size": "500-1,000 employees",
        "Headquarters": "Madrid, Spain",
        "Company Type": "Private",
        "Segment Tags": "Bioelectronic Medicine",
        "People Associated": "Grant Adams - Network Security Analyst"
    },
    {
        "Name": "PagerDuty",
        "City": "Oslo",
        "Zone": "Northwest-Northeast",
        "LinkedIn Followers": 456,
        "Industry": "Automotive",
        "Company Size": "10,000+ employees",
        "Headquarters": "Brussels, Belgium",
        "Company Type": "Public",
        "Segment Tags": "Quantum Robotics",
        "People Associated": "Leah King - Project Coordinator"
    },
    {
        "Name": "Fastly",
        "City": "Vancouver",
        "Zone": "South-East",
        "LinkedIn Followers": 56000,
        "Industry": "Retail",
        "Company Size": "100-500 employees",
        "Headquarters": "Zurich, Switzerland",
        "Company Type": "Private",
        "Segment Tags": "Augmented Analytics",
        "People Associated": "Riley Garcia - Chief Innovation Officer (CIO)"
    },
    {
        "Name": "Highspot",
        "City": "Budapest",
        "Zone": "North-West",
        "LinkedIn Followers": 7800,
        "Industry": "IT Services",
        "Company Size": "5,000-10,000 employees",
        "Headquarters": "Vienna, Austria",
        "Company Type": "Public",
        "Segment Tags": "Blockchain Identity Management",
        "People Associated": "Maya Powell - Product Owner"
    },
    {
        "Name": "Pendo.io",
        "City": "Sofia",
        "Zone": "West-North",
        "LinkedIn Followers": 90000,
        "Industry": "Aerospace",
        "Company Size": "50-100 employees",
        "Headquarters": "Helsinki, Finland",
        "Company Type": "Private",
        "Segment Tags": "Edge AI Chipsets",
        "People Associated": "Luke Turner - Customer Relationship Manager"
    },
    {
        "Name": "Xactly",
        "City": "Cairo",
        "Zone": "East-South",
        "LinkedIn Followers": 78900,
        "Industry": "Education",
        "Company Size": "1,000-5,000 employees",
        "Headquarters": "Copenhagen, Denmark",
        "Company Type": "Public",
        "Segment Tags": "Holographic Displays",
        "People Associated": "Allison Reed - Chief Experience Officer (CXO)"
    },
    {
        "Name": "ActiveCampaign",
        "City": "San Francisco",
        "Zone": "South-North",
        "LinkedIn Followers": 23400,
        "Industry": "Manufacturing",
        "Company Size": "500-1,000 employees",
        "Headquarters": "Oslo, Norway",
        "Company Type": "Private",
        "Segment Tags": "Swarm Intelligence Algorithms",
        "People Associated": "Brayden Foster - Systems Engineer"
    },
    {
        "Name": "MURAL",
        "City": "Istanbul",
        "Zone": "North-South",
        "LinkedIn Followers": 56700,
        "Industry": "IT Services",
        "Company Size": "10,000+ employees",
        "Headquarters": "Stockholm, Sweden",
        "Company Type": "Public",
        "Segment Tags": "Quantum Error Correction",
        "People Associated": "Bella White - Social Media Coordinator"
    },
    {
        "Name": "FinancialForce",
        "City": "Santiago",
        "Zone": "West-East",
        "LinkedIn Followers": 1200,
        "Industry": "Telecom",
        "Company Size": "100-500 employees",
        "Headquarters": "Warsaw, Poland",
        "Company Type": "Private",
        "Segment Tags": "Edge Processing Units",
        "People Associated": "Blake Robinson - Financial Planner"
    },
    {
        "Name": "WatchGuard Technologies ",
        "City": "Toronto",
        "Zone": "East-West",
        "LinkedIn Followers": 8900,
        "Industry": "Hospitality",
        "Company Size": "5,000-10,000 employees",
        "Headquarters": "Rome, Italy",
        "Company Type": "Public",
        "Segment Tags": "Human Augmentation",
        "People Associated": "Emma Turner - Chief Science Officer (CSO)"
    },
    {
        "Name": "ForgeRock",
        "City": "Shanghai",
        "Zone": "North-East",
        "LinkedIn Followers": 780,
        "Industry": "Agriculture",
        "Company Size": "50-100 employees",
        "Headquarters": "Vienna, Austria",
        "Company Type": "Private",
        "Segment Tags": "Quantum Internet",
        "People Associated": "Xavier Brooks - Data Engineer"
    },
    {
        "Name": "Redis ",
        "City": "New Delhi",
        "Zone": "South-West",
        "LinkedIn Followers": 234000,
        "Industry": "IT Services",
        "Company Size": "1,000-5,000 employees",
        "Headquarters": "Prague, Czech Republic",
        "Company Type": "Public",
        "Segment Tags": "Smart City Solutions",
        "People Associated": "Savannah Bennett - Chief Compliance Officer (CCO)"
    },
    {
        "Name": "Clari",
        "City": "Tokyo",
        "Zone": "Northeast-Southwest",
        "LinkedIn Followers": 87600,
        "Industry": "Healthcare",
        "Company Size": "10,000+ employees",
        "Headquarters": "Budapest, Hungary",
        "Company Type": "Private",
        "Segment Tags": "Quantum Simulation",
        "People Associated": "Eli Turner - UI Developer"
    },
    {
        "Name": "Amplitude",
        "City": "Lima",
        "Zone": "Southwest-Northeast",
        "LinkedIn Followers": 890000,
        "Industry": "Financial Services",
        "Company Size": "500-1,000 employees",
        "Headquarters": "Athens, Greece",
        "Company Type": "Public",
        "Segment Tags": "Edge-based IoT Platforms",
        "People Associated": "Zoey Garcia - Business Intelligence Analyst"
    },
    {
        "Name": "Tecsys",
        "City": "Jakarta",
        "Zone": "East-North",
        "LinkedIn Followers": 450,
        "Industry": "Real Estate",
        "Company Size": "1,000-5,000 employees",
        "Headquarters": "Lisbon, Portugal",
        "Company Type": "Private",
        "Segment Tags": "Cognitive Computing",
        "People Associated": "Cooper Parker - Chief Privacy Officer (CPO)"
    },
    {
        "Name": "Iterable",
        "City": "Manila",
        "Zone": "West-South",
        "LinkedIn Followers": 2340000,
        "Industry": "HR",
        "Company Size": "50-100 employees",
        "Headquarters": "Madrid, Spain",
        "Company Type": "Public",
        "Segment Tags": "Swarm Robotics",
        "People Associated": "Ava King - Product Marketing Manager"
    },
    {
        "Name": "Replicon",
        "City": "Mumbai",
        "Zone": "South-East",
        "LinkedIn Followers": 120,
        "Industry": "IT Services",
        "Company Size": "5,000-10,000 employees",
        "Headquarters": "Brussels, Belgium",
        "Company Type": "Private",
        "Segment Tags": "Edge Machine Learning",
        "People Associated": "Wyatt Thomas - Solutions Architect"
    },
    {
        "Name": "Couchbase",
        "City": "Seoul",
        "Zone": "North-West",
        "LinkedIn Followers": 560000,
        "Industry": "Entertainment",
        "Company Size": "500-1,000 employees",
        "Headquarters": "Zurich, Switzerland",
        "Company Type": "Public",
        "Segment Tags": "Personalized Medicine Technology",
        "People Associated": "Maya Foster - Corporate Trainer"
    },
    {
        "Name": "Cloudbeds",
        "City": "Brussels",
        "Zone": "Southwest-East",
        "LinkedIn Followers": 9000,
        "Industry": "Energy",
        "Company Size": "10,000+ employees",
        "Headquarters": "Vienna, Austria",
        "Company Type": "Private",
        "Segment Tags": "Quantum Cryptocurrencies",
        "People Associated": "Carson Hill - Chief Resilience Officer (CRO)"
    },
    {
        "Name": "Amelia (Formerly IPsoft)",
        "City": "Berlin",
        "Zone": "Southeast-West",
        "LinkedIn Followers": 5670,
        "Industry": "Retail",
        "Company Size": "50-100 employees",
        "Headquarters": "Helsinki, Finland",
        "Company Type": "Public",
        "Segment Tags": "Autonomous Underwater Vehicles",
        "People Associated": "Violet Turner - Chief Analytics Officer (CAO)"
    },
    {
        "Name": "CircleCI",
        "City": "Warsaw",
        "Zone": "Northwest-South",
        "LinkedIn Followers": 34500,
        "Industry": "Manufacturing",
        "Company Size": "100-500 employees",
        "Headquarters": "Copenhagen, Denmark",
        "Company Type": "Private",
        "Segment Tags": "Edge Sensor Networks",
        "People Associated": "Owen Adams - Technical Project Manager"
    },
    {
        "Name": "airSlate",
        "City": "Vienna",
        "Zone": "Northeast-West",
        "LinkedIn Followers": 67800,
        "Industry": "Automotive",
        "Company Size": "1,000-5,000 employees",
        "Headquarters": "Oslo, Norway",
        "Company Type": "Public",
        "Segment Tags": "Humanoid Robotics",
        "People Associated": "Naomi Lewis - Chief Ethics Officer (CEO)"
    },
    {
        "Name": "pipefy",
        "City": "Amsterdam",
        "Zone": "South-South",
        "LinkedIn Followers": 78000,
        "Industry": "Education",
        "Company Size": "5,000-10,000 employees",
        "Headquarters": "Stockholm, Sweden",
        "Company Type": "Private",
        "Segment Tags": "Quantum Sensing",
        "People Associated": "Leo Robinson - IT Auditor"
    },
    {
        "Name": "celigo",
        "City": "Barcelona",
        "Zone": "North-North",
        "LinkedIn Followers": 4560,
        "Industry": "Telecom",
        "Company Size": "10,000+ employees",
        "Headquarters": "Warsaw, Poland",
        "Company Type": "Public",
        "Segment Tags": "Edge Blockchain",
        "People Associated": "Grace Turner - Product Designer"
    },
    {
        "Name": "Notarize",
        "City": "Prague",
        "Zone": "East-East",
        "LinkedIn Followers": 9870000,
        "Industry": "HR",
        "Company Size": "500-1,000 employees",
        "Headquarters": "Rome, Italy",
        "Company Type": "Private",
        "Segment Tags": "Emotion AI",
        "People Associated": "Owen White - Chief Learning Officer (CLO)"
    },
    {
        "Name": "Cisive",
        "City": "Stockholm",
        "Zone": "West-West",
        "LinkedIn Followers": 1230000,
        "Industry": "IT Services",
        "Company Size": "50-100 employees",
        "Headquarters": "Vienna, Austria",
        "Company Type": "Public",
        "Segment Tags": "Autonomous Flying Cars",
        "People Associated": "Stella Adams - Business Process Analyst"
    },
    {
        "Name": "Piano",
        "City": "Zurich",
        "Zone": "Northeast-East",
        "LinkedIn Followers": 89000,
        "Industry": "Agriculture",
        "Company Size": "1,000-5,000 employees",
        "Headquarters": "Prague, Czech Republic",
        "Company Type": "Private",
        "Segment Tags": "Quantum Metrology",
        "People Associated": "Caleb Turner - Chief Knowledge Officer (CKO)"
    },
    {
        "Name": "Workwave",
        "City": "Helsinki",
        "Zone": "Southwest-West",
        "LinkedIn Followers": 12300000,
        "Industry": "Healthcare",
        "Company Size": "100-500 employees",
        "Headquarters": "Budapest, Hungary",
        "Company Type": "Public",
        "Segment Tags": "Edge Cloud Computing",
        "People Associated": "Nora Foster - UI/UX Developer"
    },
    {
        "Name": "Ridgeline",
        "City": "Moscow",
        "Zone": "Southeast-Northwest",
        "LinkedIn Followers": 78900000,
        "Industry": "Financial Services",
        "Company Size": "10,000+ employees",
        "Headquarters": "Athens, Greece",
        "Company Type": "Private",
        "Segment Tags": "Precision Agriculture Technology",
        "People Associated": "Miles Butler - Chief Happiness Officer (CHO)"
    },
    {
        "Name": "Appspace",
        "City": "Rio de Janeiro",
        "Zone": "Northwest-Southeast",
        "LinkedIn Followers": 78900000,
        "Industry": "Real Estate",
        "Company Size": "5,000-10,000 employees",
        "Headquarters": "Lisbon, Portugal",
        "Company Type": "Public",
        "Segment Tags": "Quantum Battery Technology",
        "People Associated": "Harper King - Supply Chain Manager"
    },
    {
        "Name": "SYSPRO",
        "City": "Cape Town",
        "Zone": "South-Southeast",
        "LinkedIn Followers": 120000,
        "Industry": "Entertainment",
        "Company Size": "50-100 employees",
        "Headquarters": "Madrid, Spain",
        "Company Type": "Private",
        "Segment Tags": "Edge Computing Analytics",
        "People Associated": "Ashton Turner - Software Architect"
    },
    {
        "Name": "Pantheon",
        "City": "Mexico City",
        "Zone": "North-Northeast",
        "LinkedIn Followers": 8900000,
        "Industry": "IT Services",
        "Company Size": "500-1,000 employees",
        "Headquarters": "Brussels, Belgium",
        "Company Type": "Public",
        "Segment Tags": "Emotional Analytics",
        "People Associated": "Taylor Carter - Chief Visionary Officer (CVO)"
    },
    {
        "Name": "LeanData",
        "City": "Dubai",
        "Zone": "East-Southeast",
        "LinkedIn Followers": 789000,
        "Industry": "Retail",
        "Company Size": "1,000-5,000 employees",
        "Headquarters": "Zurich, Switzerland",
        "Company Type": "Private",
        "Segment Tags": "Autonomous Robotic Surgery",
        "People Associated": "Riley Mitchell - Enterprise Architect"
    },
    {
        "Name": "Jivox",
        "City": "Bangkok",
        "Zone": "West-Northwest",
        "LinkedIn Followers": 456000,
        "Industry": "Manufacturing",
        "Company Size": "10,000+ employees",
        "Headquarters": "Vienna, Austria",
        "Company Type": "Public",
        "Segment Tags": "Quantum Security",
        "People Associated": "Autumn Foster - Chief Wellness Officer (CWO)"
    },
    {
        "Name": "Arcoro",
        "City": "Kuala Lumpur",
        "Zone": "Southeast-Southwest",
        "LinkedIn Followers": 7890,
        "Industry": "Aerospace",
        "Company Size": "50-100 employees",
        "Headquarters": "Helsinki, Finland",
        "Company Type": "Private",
        "Segment Tags": "Edge AI Accelerators",
        "People Associated": "Landon Turner - Data Privacy Specialist"
    },
    {
        "Name": "Librestream",
        "City": "Los Angeles",
        "Zone": "Southwest-Northeast",
        "LinkedIn Followers": 678000,
        "Industry": "Energy",
        "Company Size": "100-500 employees",
        "Headquarters": "Copenhagen, Denmark",
        "Company Type": "Public",
        "Segment Tags": "Swarm Drones",
        "People Associated": "Hannah Davis - Chief Inclusion Officer (CIO)"
    }
]